aio_pubsub/__init__.py
aio_pubsub/_version.py
aio_pubsub/interfaces.py
aio_pubsub/typings.py
aio_pubsub/backends/__init__.py
aio_pubsub/backends/memory.py
aio_pubsub/backends/postgresql.py
aio_pubsub/backends/redis.py
aio_pubsub-0.3.0.dist-info/LICENSE
aio_pubsub-0.3.0.dist-info/METADATA
aio_pubsub-0.3.0.dist-info/WHEEL
aio_pubsub-0.3.0.dist-info/top_level.txt
aio_pubsub-0.3.0.dist-info/RECORD
