Metadata-Version: 2.1
Name: aio-pubsub
Version: 0.3.0
Summary: A generic interface wrapping multiple backends to provide a consistent pubsub API.
Home-page: http://github.com/bruziev/async_pubsub
Author: Bakhtiyor Ruziev
Author-email: bakhtiyor.ruziev@yandex.ru
License: UNKNOWN
Keywords: pubsub pub/sub mongodb
Platform: UNKNOWN
Classifier: Development Status :: 3 - Alpha
Classifier: Intended Audience :: Developers
Classifier: Programming Language :: Python
Classifier: Programming Language :: Python :: 3.6
Classifier: Programming Language :: Python :: 3.7
Classifier: Programming Language :: Python :: Implementation :: CPython
Classifier: Topic :: Software Development :: Libraries :: Python Modules
Classifier: License :: OSI Approved :: MIT License
Provides-Extra: aiopg
Requires-Dist: aiopg (>=1.0.0) ; extra == 'aiopg'
Provides-Extra: aioredis
Requires-Dist: aioredis (>=1.2.0) ; extra == 'aioredis'
